super_search/NoneDecoder.py
super_search/SuperSearch.py
super_search/__init__.py
super_search_gpt-0.1.4.dist-info/METADATA
super_search_gpt-0.1.4.dist-info/WHEEL
super_search_gpt-0.1.4.dist-info/top_level.txt
super_search_gpt-0.1.4.dist-info/RECORD
