Metadata-Version: 2.1
Name: super-search-gpt
Version: 0.1.4
Summary: SuperSearch is a powerful Python package for advanced search and data extraction. It leverages the GPT-4 AI model, Google search, and web scraping to efficiently obtain information on various topics. Ideal for developers needing quick, accurate responses to complex queries and data extraction, analysis, and summarization from multiple web sources. Easy to integrate, SuperSearch enhances functionality and user experience, saving time on manual research and enabling smarter, more effectiv
Home-page: https://github.com/gershonavi/super_search
Author: Avi Gershon
Author-email: gershonavi@gmail.com
Classifier: Development Status :: 3 - Alpha
Classifier: Intended Audience :: Developers
Classifier: License :: OSI Approved :: MIT License
Classifier: Programming Language :: Python :: 3
Classifier: Programming Language :: Python :: 3.6
Classifier: Programming Language :: Python :: 3.7
Classifier: Programming Language :: Python :: 3.8
Classifier: Programming Language :: Python :: 3.9
Requires-Python: >=3.6
Requires-Dist: googlesearch-python
Requires-Dist: beautifulsoup4
Requires-Dist: openai
Requires-Dist: pandas
Requires-Dist: requests-html
Requires-Dist: requests
